fms_acceleration/__init__.py
fms_acceleration/accelerator_patcher.py
fms_acceleration/cli.py
fms_acceleration/constants.py
fms_acceleration/framework.py
fms_acceleration/framework_plugin.py
fms_acceleration/model_patcher.py
fms_acceleration/utils/__init__.py
fms_acceleration/utils/test_utils.py
fms_acceleration-0.6.4.dist-info/METADATA
fms_acceleration-0.6.4.dist-info/WHEEL
fms_acceleration-0.6.4.dist-info/RECORD
