Metadata-Version: 2.4
Name: fms-acceleration
Version: 0.6.4
Summary: FMS Acceleration Plugin Framework
Author-email: Fabian Lim <flim@sg.ibm.com>
License: Apache-2.0
Keywords: acceleration,fms-hf-tuning
Classifier: Development Status :: 4 - Beta
Classifier: License :: OSI Approved :: Apache Software License
Classifier: Programming Language :: Python :: 3
Classifier: Programming Language :: Python :: 3.9
Classifier: Programming Language :: Python :: 3.10
Classifier: Programming Language :: Python :: 3.11
Requires-Python: ~=3.9
Requires-Dist: accelerate
Requires-Dist: numpy<2.0
Requires-Dist: pandas
Requires-Dist: peft>=0.15.0
Requires-Dist: torch>2.2
